boardinator/__init__.py
boardinator/assets/chesscom.png
boardinator/boardinator.py
boardinator-0.1.0.dist-info/LICENSE
boardinator-0.1.0.dist-info/METADATA
boardinator-0.1.0.dist-info/WHEEL
boardinator-0.1.0.dist-info/RECORD
