Metadata-Version: 2.1
Name: boardinator
Version: 0.1.0
Summary: A tool made to generate custom Chess.com boards from the terminal.
License: MIT
Author: Nathan Solis
Author-email: 66754842+coldenate@users.noreply.github.com
Requires-Python: >=3.11,<4.0
Classifier: License :: OSI Approved :: MIT License
Classifier: Programming Language :: Python :: 3
Classifier: Programming Language :: Python :: 3.11
Requires-Dist: numpy (>=1.24.3,<2.0.0)
Requires-Dist: pillow (>=9.5.0,<10.0.0)
